easy_api_test/__init__.py
easy_api_test/__main__.py
easy_api_test/core/__init__.py
easy_api_test/core/api.py
easy_api_test/core/config_reader.py
easy_api_test/core/http_client.py
easy_api_test/core/logger.py
easy_api_test/data/bootstrap.min.css
easy_api_test/data/echarts.min.js
easy_api_test/data/jquery.min.js
easy_api_test/utils/__init__.py
easy_api_test/utils/cli.py
easy_api_test/utils/generate.py
easy_api_test/utils/parser.py
easy_api_test/utils/tools.py
easy_api_test-0.1.6.dist-info/METADATA
easy_api_test-0.1.6.dist-info/WHEEL
easy_api_test-0.1.6.dist-info/RECORD
