Metadata-Version: 2.4
Name: easy_api_test
Version: 0.1.6
Summary: API测试工具
Author-email: liulangjuanzhou <liulangjuanzhou@gmail.com>
Requires-Python: >=3.7
Requires-Dist: jsonpath-ng>=1.7.0
Requires-Dist: lljz-tools>=0.3.7
Requires-Dist: pytest>=6.0.0
Requires-Dist: pyyaml>=5.4.0
Requires-Dist: requests>=2.25.0
